{
    "name": "scene",
    "objects": [
        {
            "type": "LIGHT",
            "name": "Light",
            "transform": {
                "translation": [
                    -3.3411130905151367,
                    -16.499208450317383,
                    39.137657165527344
                ],
                "rotation": [
                    9.68732738494873,
                    15.594269752502441,
                    43.30875015258789
                ],
                "scaling": [
                    1.0,
                    0.9999999403953552,
                    1.0
                ]
            }
        },
        {
            "type": "CAMERA",
            "name": "Camera",
            "transform": {
                "translation": [
                    7.358891487121582,
                    -6.925790786743164,
                    12.958309173583984
                ],
                "rotation": [
                    27.70457649230957,
                    11.957837104797363,
                    19.30132293701172
                ],
                "scaling": [
                    1.0,
                    1.0,
                    1.0
                ]
            }
        },
        {
            "type": "MESH",
            "name": "ground",
            "transform": {
                "translation": [
                    1.5583120584487915,
                    0.0,
                    0.0
                ],
                "rotation": [
                    40.51423645019531,
                    0.0,
                    0.0
                ],
                "scaling": [
                    5.103424072265625,
                    5.103424072265625,
                    5.103424072265625
                ]
            },
            "file_name": "ground"
        },
        {
            "type": "MESH",
            "name": "tenQ",
            "transform": {
                "translation": [
                    1.5583120584487915,
                    -0.15516000986099243,
                    6.520002365112305
                ],
                "rotation": [
                    40.51423645019531,
                    0.0,
                    0.0
                ],
                "scaling": [
                    4.036628723144531,
                    3.0013267993927,
                    3.0013267993927
                ]
            },
            "file_name": "tenQ"
        },
        {
            "type": "MESH",
            "name": "castle",
            "transform": {
                "translation": [
                    0.0,
                    0.0,
                    7.880633354187012
                ],
                "rotation": [
                    40.51423645019531,
                    0.0,
                    0.0
                ],
                "scaling": [
                    8.0,
                    8.0,
                    8.0
                ]
            },
            "file_name": "castle"
        },
        {
            "type": "MESH",
            "name": "kabe",
            "transform": {
                "translation": [
                    -71.64115142822266,
                    -102.27962493896484,
                    5.761873245239258
                ],
                "rotation": [
                    0.0,
                    0.0,
                    0.0
                ],
                "scaling": [
                    6.026207447052002,
                    34.79353332519531,
                    6.205272197723389
                ]
            },
            "file_name": "kabe"
        },
        {
            "type": "MESH",
            "name": "kabe.001",
            "transform": {
                "translation": [
                    60.13008117675781,
                    72.87966918945312,
                    6.444376468658447
                ],
                "rotation": [
                    0.0,
                    0.0,
                    0.0
                ],
                "scaling": [
                    6.026207447052002,
                    24.904531478881836,
                    6.205272197723389
                ]
            },
            "file_name": "kabe"
        },
        {
            "type": "MESH",
            "name": "kabe.002",
            "transform": {
                "translation": [
                    36.82381820678711,
                    39.764305114746094,
                    6.163857460021973
                ],
                "rotation": [
                    0.0,
                    0.0,
                    0.0
                ],
                "scaling": [
                    27.334850311279297,
                    7.729187965393066,
                    6.205272197723389
                ]
            },
            "file_name": "kabe"
        },
        {
            "type": "MESH",
            "name": "kabe.003",
            "transform": {
                "translation": [
                    -48.032875061035156,
                    -59.13032150268555,
                    6.143497943878174
                ],
                "rotation": [
                    0.0,
                    0.0,
                    0.0
                ],
                "scaling": [
                    27.334850311279297,
                    7.729187965393066,
                    6.205272197723389
                ]
            },
            "file_name": "kabe"
        }
    ]
}